pyBAv3/BAv2.py
pyBAv3/__init__.py
pyBAv3-0.1.dist-info/METADATA
pyBAv3-0.1.dist-info/WHEEL
pyBAv3-0.1.dist-info/top_level.txt
pyBAv3-0.1.dist-info/RECORD
