Metadata-Version: 2.1
Name: pyBAv3
Version: 0.1
Summary: BAv2 is simple personalised  chatbot for every user and developer
Author: srinadhch07
Author-email: <srinadhc07@gmail.com>
Keywords: chatbot,ai,python,pyBAv
Classifier: Intended Audience :: Developers
Classifier: Topic :: Software Development :: Build Tools
Classifier: License :: OSI Approved :: MIT License
Classifier: Programming Language :: Python :: 3.8
Classifier: Programming Language :: Python :: 3.9
Classifier: Programming Language :: Python :: 3.10
